CHANGES.txt
LICENSE.txt
MANIFEST.in
README.md
TODO.txt
demo.py
pyproject.toml
setup.cfg
setup.py
tox.ini
src/imagehelper/__init__.py
src/imagehelper/_io.py
src/imagehelper/_types.py
src/imagehelper/errors.py
src/imagehelper/image_wrapper.py
src/imagehelper/py.typed
src/imagehelper/resizer.py
src/imagehelper/utils.py
src/imagehelper.egg-info/PKG-INFO
src/imagehelper.egg-info/SOURCES.txt
src/imagehelper.egg-info/dependency_links.txt
src/imagehelper.egg-info/not-zip-safe
src/imagehelper.egg-info/requires.txt
src/imagehelper.egg-info/top_level.txt
src/imagehelper/saver/__init__.py
src/imagehelper/saver/_core.py
src/imagehelper/saver/localfile.py
src/imagehelper/saver/s3.py
src/imagehelper/saver/utils.py
tests/__init__.py
tests/test_core.py
tests/test-data/henry.jpg
tests/test-data/spiral_animation.gif