Metadata-Version: 2.4
Name: imagehelper
Version: 0.8.0
Summary: Simple utilites for image resizing and uploading and stuff like that.
Home-page: http://github.com/jvanasco/imagehelper
Author: Jonathan Vanasco
Author-email: jonathan@findmeon.com
License: BSD
Classifier: Programming Language :: Python :: 3
Classifier: Programming Language :: Python :: 3.6
Classifier: Programming Language :: Python :: 3.7
Classifier: Programming Language :: Python :: 3.8
Classifier: Programming Language :: Python :: 3.9
Classifier: Programming Language :: Python :: 3.10
Classifier: Programming Language :: Python :: 3.11
Classifier: Intended Audience :: Developers
Classifier: Topic :: Multimedia :: Graphics :: Graphics Conversion
Classifier: Topic :: Software Development :: Libraries :: Python Modules
License-File: LICENSE.txt
Requires-Dist: envoy
Requires-Dist: Pillow
Requires-Dist: typing_extensions
Provides-Extra: testing
Requires-Dist: boto3; extra == "testing"
Requires-Dist: mypy-boto3-s3; extra == "testing"
Requires-Dist: pytest; extra == "testing"
Requires-Dist: requests; extra == "testing"
Requires-Dist: types-Pillow; extra == "testing"
Requires-Dist: types-requests; extra == "testing"
Dynamic: author
Dynamic: author-email
Dynamic: classifier
Dynamic: description
Dynamic: description-content-type
Dynamic: home-page
Dynamic: license
Dynamic: license-file
Dynamic: provides-extra
Dynamic: requires-dist
Dynamic: summary
